LICENSE
README.md
setup.py
pxolly/__init__.py
pxolly/abc.py
pxolly/api.py
pxolly/const.py
pxolly/exceptions.py
pxolly.egg-info/PKG-INFO
pxolly.egg-info/SOURCES.txt
pxolly.egg-info/dependency_links.txt
pxolly.egg-info/requires.txt
pxolly.egg-info/top_level.txt
pxolly/categories/__init__.py
pxolly/categories/acc.py
pxolly/categories/base.py
pxolly/categories/callback.py
pxolly/models/__init__.py
pxolly/models/acc/__init__.py
pxolly/models/acc/get_info.py
pxolly/models/callback/__init__.py
pxolly/models/callback/get_settings.py