Metadata-Version: 2.1
Name: pxolly
Version: 1.0.2
Summary: pxolly API wrapper
Home-page: https://github.com/lordralinc/pxolly_api
Author: lordralinc
License: MIT
Platform: UNKNOWN
Classifier: Programming Language :: Python :: 3.7
Classifier: Programming Language :: Python :: 3.8
Classifier: Programming Language :: Python :: 3.9
Classifier: Operating System :: OS Independent
